ms/__init__.py
ms/base.py
ms/generate_proto_file.py
ms/ms-plugin.py
ms/protocol_pb2.py
ms/rpc.py
ms_tournament/__init__.py
ms_tournament/base.py
ms_tournament/generate_proto_file.py
ms_tournament/ms-admin-plugin.py
ms_tournament/protocol_admin_pb2.py
ms_tournament/rpc.py
ms_api-0.10.103.dist-info/METADATA
ms_api-0.10.103.dist-info/WHEEL
ms_api-0.10.103.dist-info/top_level.txt
ms_api-0.10.103.dist-info/RECORD
