Metadata-Version: 2.1
Name: ms-api
Version: 0.10.103
Summary: Python wrapper for the Mahjong Soul (Majsoul) Protobuf objects. It allows to use their API.
Home-page: https://github.com/MahjongRepository/mahjong_soul_api
Author: Nihisil
Author-email: alexey@nihisil.com
License: UNKNOWN
Platform: UNKNOWN
Classifier: Development Status :: 5 - Production/Stable
Classifier: Environment :: Console
Classifier: Intended Audience :: Developers
Classifier: License :: OSI Approved :: MIT License
Classifier: Programming Language :: Python :: 3.7
Classifier: Programming Language :: Python :: 3.8
Classifier: Programming Language :: Python :: 3.9
Requires-Dist: aiohttp (==3.7.4.post0)
Requires-Dist: protobuf (==3.18.0)
Requires-Dist: websockets (==10.0)
